rpcm/__about__.py
rpcm/__init__.py
rpcm/__main__.py
rpcm/cli.py
rpcm/geo.py
rpcm/rpc_file_readers.py
rpcm/rpc_model.py
rpcm/utils.py
rpcm-1.4.10.dist-info/LICENSE
rpcm-1.4.10.dist-info/METADATA
rpcm-1.4.10.dist-info/WHEEL
rpcm-1.4.10.dist-info/entry_points.txt
rpcm-1.4.10.dist-info/top_level.txt
rpcm-1.4.10.dist-info/RECORD
