Metadata-Version: 2.1
Name: rpcm
Version: 1.4.10
Summary: Rational Polynomial Camera Model for optical satellite images.
Home-page: https://github.com/centreborelli/rpcm
Author: Carlo de Franchis
Author-email: carlo.de-franchis@ens-paris-saclay.fr
License: UNKNOWN
Platform: UNKNOWN
Requires-Python: >=3
Provides-Extra: test
License-File: LICENSE
